meoaw/__init__.py
meoaw/meoaw.py
meoawji-1.0.1.dist-info/LICENSE
meoawji-1.0.1.dist-info/METADATA
meoawji-1.0.1.dist-info/WHEEL
meoawji-1.0.1.dist-info/top_level.txt
meoawji-1.0.1.dist-info/RECORD
