Metadata-Version: 2.1
Name: meoawji
Version: 1.0.1
Summary: Free uptime bot in replit with module !
Home-page: https://discord.gg/nUXkXEyBBM
Author: GxdjCoding
Author-email: meoawcute@gmail.com
License: MIT
Classifier: Programming Language :: Python :: 3
Classifier: Development Status :: 4 - Beta
Classifier: License :: OSI Approved :: MIT License
Classifier: Operating System :: OS Independent
License-File: LICENSE
